ae_app/__init__.py
ae_app/admin.py
ae_app/apps.py
ae_app/models.py
ae_app/tests.py
ae_app/views.py
ae_app/migrations/__init__.py
inte_ae/__init__.py
inte_ae/action_items.py
inte_ae/admin_site.py
inte_ae/apps.py
inte_ae/baker_recipes.py
inte_ae/choices.py
inte_ae/constants.py
inte_ae/list_data.py
inte_ae/urls.py
inte_ae/admin/__init__.py
inte_ae/admin/ae_followup_admin.py
inte_ae/admin/ae_initial_admin.py
inte_ae/admin/ae_susar_admin.py
inte_ae/admin/ae_tmg_admin.py
inte_ae/admin/death_report_admin.py
inte_ae/admin/death_report_tmg_admin.py
inte_ae/admin/death_report_tmg_second_admin.py
inte_ae/forms/__init__.py
inte_ae/forms/ae_followup_form.py
inte_ae/forms/ae_initial_form.py
inte_ae/forms/ae_susar_form.py
inte_ae/forms/ae_tmg_form.py
inte_ae/forms/death_report_form.py
inte_ae/forms/death_report_tmg_form.py
inte_ae/forms/death_report_tmg_second_form.py
inte_ae/migrations/0001_initial.py
inte_ae/migrations/__init__.py
inte_ae/models/__init__.py
inte_ae/models/ae_followup.py
inte_ae/models/ae_initial.py
inte_ae/models/ae_susar.py
inte_ae/models/ae_tmg.py
inte_ae/models/death_report.py
inte_ae/models/death_report_tmg.py
inte_ae/models/death_report_tmg_second.py
inte_ae/models/managers.py
inte_ae/models/model_mixins.py
inte_ae/pdf_reports/__init__.py
inte_ae/pdf_reports/ae_report.py
inte_ae/pdf_reports/death_report.py
inte_ae/pdf_reports/inte_pdf_report_mixin.py
inte_ae/templates/inte_ae/bootstrap3/ae_initial_description.html
inte_ae/templatetags/__init__.py
inte_ae/templatetags/inte_ae_extras.py
inte_ae/tests/__init__.py
inte_ae/tests/test_actions.py
inte_ae/tests/urls.py
inte_ae-0.1.5.dist-info/AUTHORS
inte_ae-0.1.5.dist-info/LICENSE
inte_ae-0.1.5.dist-info/METADATA
inte_ae-0.1.5.dist-info/WHEEL
inte_ae-0.1.5.dist-info/top_level.txt
inte_ae-0.1.5.dist-info/RECORD
