Metadata-Version: 2.1
Name: inte-ae
Version: 0.1.5
Summary: Adverse Event models and handling.
Home-page: https://github.com/inte-africa-trialtrial/inte-ae
Author: Erik van Widenfelt
Author-email: ew2789@gmail.com
License: GPL license, see LICENSE
Keywords: django inte adverse event
Platform: UNKNOWN
Classifier: Environment :: Web Environment
Classifier: Framework :: Django
Classifier: Intended Audience :: Developers
Classifier: Intended Audience :: Science/Research
Classifier: License :: OSI Approved :: GNU General Public License v3 (GPLv3)
Classifier: Operating System :: OS Independent
Classifier: Programming Language :: Python :: 3.7
Classifier: Topic :: Internet :: WWW/HTTP
Classifier: Topic :: Internet :: WWW/HTTP :: Dynamic Content
Requires-Python: >=3.7
Requires-Dist: django-collect-offline
Requires-Dist: django-collect-offline-files
Requires-Dist: edc-action-item
Requires-Dist: edc-adverse-event
Requires-Dist: edc-form-describer
Requires-Dist: edc-reportable
Requires-Dist: edc-subject-dashboard
Requires-Dist: edc-metadata
Requires-Dist: edc-model
Requires-Dist: edc-notification
Requires-Dist: edc-sites
Requires-Dist: edc-utils
